sber_tunnel/__init__.py
sber_tunnel/cli/__init__.py
sber_tunnel/cli/main.py
sber_tunnel/core/__init__.py
sber_tunnel/core/cert_handler.py
sber_tunnel/core/config.py
sber_tunnel/core/utils.py
sber_tunnel/models/__init__.py
sber_tunnel/models/manifest.py
sber_tunnel/services/__init__.py
sber_tunnel/services/confluence.py
sber_tunnel/services/file_manager.py
sber_tunnel-2.4.0.dist-info/METADATA
sber_tunnel-2.4.0.dist-info/WHEEL
sber_tunnel-2.4.0.dist-info/entry_points.txt
sber_tunnel-2.4.0.dist-info/top_level.txt
sber_tunnel-2.4.0.dist-info/RECORD
