Metadata-Version: 2.4
Name: sber-tunnel
Version: 2.4.0
Summary: CLI для передачи файлов между директориями через Confluence API
Author: apaem
Author-email: apaem <emila1998@yandex.ru>
License: MIT
Requires-Python: >=3.8
Requires-Dist: click>=8.1.0
Requires-Dist: atlassian-python-api>=3.41.0
Requires-Dist: requests>=2.31.0
Requires-Dist: cryptography>=41.0.0
Dynamic: author
Dynamic: requires-python
